nowcasting_dataloader/__init__.py
nowcasting_dataloader/batch.py
nowcasting_dataloader/datamodules.py
nowcasting_dataloader/datasets.py
nowcasting_dataloader/fake.py
nowcasting_dataloader/subset.py
nowcasting_dataloader/xr_utils.py
nowcasting_dataloader/data_sources/__init__.py
nowcasting_dataloader/data_sources/datasource_output.py
nowcasting_dataloader/data_sources/gsp/__init__.py
nowcasting_dataloader/data_sources/gsp/gsp_model.py
nowcasting_dataloader/data_sources/metadata/__init__.py
nowcasting_dataloader/data_sources/metadata/metadata_model.py
nowcasting_dataloader/data_sources/nwp/__init__.py
nowcasting_dataloader/data_sources/nwp/nwp_model.py
nowcasting_dataloader/data_sources/opticalflow/__init__.py
nowcasting_dataloader/data_sources/opticalflow/opticalflow_model.py
nowcasting_dataloader/data_sources/pv/__init__.py
nowcasting_dataloader/data_sources/pv/pv_model.py
nowcasting_dataloader/data_sources/satellite/__init__.py
nowcasting_dataloader/data_sources/satellite/satellite_model.py
nowcasting_dataloader/data_sources/sun/__init__.py
nowcasting_dataloader/data_sources/sun/sun_model.py
nowcasting_dataloader/data_sources/topographic/__init__.py
nowcasting_dataloader/data_sources/topographic/topographic_model.py
nowcasting_dataloader-2.0.6.dist-info/LICENSE
nowcasting_dataloader-2.0.6.dist-info/METADATA
nowcasting_dataloader-2.0.6.dist-info/WHEEL
nowcasting_dataloader-2.0.6.dist-info/top_level.txt
nowcasting_dataloader-2.0.6.dist-info/RECORD
