Metadata-Version: 2.1
Name: nowcasting-dataloader
Version: 2.0.6
Summary: Nowcasting Dataloader
Author: Jack Kelly, Peter Dudfield, Jacob Bieker
Author-email: info@openclimatefix.org
License: MIT
License-File: LICENSE
Requires-Dist: nowcasting-dataset
Requires-Dist: torch
Requires-Dist: pytorch-lightning
Requires-Dist: einops
Requires-Dist: boto3
